sdypy/io/__init__.py
sdypy/io/sfmov/__init__.py
sdypy/io/sfmov/sfmov.py
sdypy_io-0.3.1.dist-info/METADATA
sdypy_io-0.3.1.dist-info/WHEEL
sdypy_io-0.3.1.dist-info/RECORD
