Metadata-Version: 2.4
Name: sdypy-io
Version: 0.3.1
Summary: Reading and writing of data in structural dynamics.
Project-URL: homepage, https://github.com/sdypy/sdypy-io
Project-URL: documentation, https://sdypy-io.readthedocs.io/en/latest/index.html
Project-URL: source, https://github.com/sdypy/sdypy-io
Author-email: "Janko Slavič et al." <janko.slavic@fs.uni-lj.si>
Maintainer-email: "Janko Slavič et al." <janko.slavic@fs.uni-lj.si>
License-Expression: MIT
Keywords: LVM,MRAW,UFF,UNV,Universal File Format,io,read/write,structural dynamics
Classifier: Development Status :: 5 - Production/Stable
Classifier: Intended Audience :: Developers
Classifier: License :: OSI Approved :: MIT License
Classifier: Programming Language :: Python :: 3.10
Classifier: Topic :: Scientific/Engineering
Requires-Python: >=3.10
Requires-Dist: lvm-read==1.20
Requires-Dist: pymraw>=0.30
Requires-Dist: pyuff==2.1
Provides-Extra: dev
Requires-Dist: build; extra == 'dev'
Requires-Dist: pytest; extra == 'dev'
Requires-Dist: sphinx; extra == 'dev'
Requires-Dist: sphinx-copybutton>=0.5.2; extra == 'dev'
Requires-Dist: sphinx-rtd-theme; extra == 'dev'
Requires-Dist: twine; extra == 'dev'
Requires-Dist: wheel; extra == 'dev'
